nbdev_tests/__init__.py
nbdev_tests/_modidx.py
nbdev_tests/card.py
nbdev_tests-0.0.1.dist-info/LICENSE
nbdev_tests-0.0.1.dist-info/METADATA
nbdev_tests-0.0.1.dist-info/WHEEL
nbdev_tests-0.0.1.dist-info/entry_points.txt
nbdev_tests-0.0.1.dist-info/top_level.txt
nbdev_tests-0.0.1.dist-info/RECORD
