Metadata-Version: 2.1
Name: nbdev-tests
Version: 0.0.1
Summary: test
Home-page: https://github.com/YolandaSunYS/nbdev-tests
Author: Ying Sun
Author-email: ying.sun@rakuten.com
License: Apache Software License 2.0
Keywords: n,b,d,e,v, ,j,u,p,y,t,e,r, ,n,o,t,e,b,o,o,k, ,p,y,t,h,o,n
Classifier: Development Status :: 4 - Beta
Classifier: Intended Audience :: Developers
Classifier: Natural Language :: English
Classifier: Programming Language :: Python :: 3.7
Classifier: Programming Language :: Python :: 3.8
Classifier: Programming Language :: Python :: 3.9
Classifier: Programming Language :: Python :: 3.10
Classifier: License :: OSI Approved :: Apache Software License
Requires-Python: >=3.7
License-File: LICENSE
Requires-Dist: fastcore
Requires-Dist: pandas
Provides-Extra: dev
